sample/__init__.py
sample/package_data.dat
test85910_sample-1.2.0.data/data/my_data/data_file
test85910_sample-1.2.0.dist-info/DESCRIPTION.rst
test85910_sample-1.2.0.dist-info/METADATA
test85910_sample-1.2.0.dist-info/RECORD
test85910_sample-1.2.0.dist-info/WHEEL
test85910_sample-1.2.0.dist-info/entry_points.txt
test85910_sample-1.2.0.dist-info/metadata.json
test85910_sample-1.2.0.dist-info/top_level.txt
